[
    {
        "@id": "http://www.wikidata.org/entity/Q4913955",
        "type": "Feature",
        "properties": {
            "title": "Binchester Roman Fort",
            "summary": "Roman fort in County Durham, England, UK",
            "reciprocal": false
        },
        "links": [
            {
                "type": "closeMatch",
                "identifier": "https://pleiades.stoa.org/places/89316"
            }
        ]
    },
    {
        "@id": "https://edh.ub.uni-heidelberg.de/edh/geographie/G004006",
        "type": "Feature",
        "properties": {
            "title": "Vinovia",
            "summary": null,
            "reciprocal": false
        },
        "links": [
            {
                "type": "closeMatch",
                "identifier": "https://pleiades.stoa.org/places/89316"
            },
            {
                "type": "closeMatch",
                "identifier": "https://www.trismegistos.org/place/13688"
            }
        ]
    },
    {
        "@id": "https://edh.ub.uni-heidelberg.de/edh/geographie/G004300",
        "type": "Feature",
        "properties": {
            "title": "Vinovia (Lager, Praetorium {Thermen})",
            "summary": null,
            "reciprocal": false
        },
        "links": [
            {
                "type": "closeMatch",
                "identifier": "https://pleiades.stoa.org/places/89316"
            },
            {
                "type": "closeMatch",
                "identifier": "https://www.trismegistos.org/place/13688"
            }
        ]
    },
    {
        "@id": "https://edh.ub.uni-heidelberg.de/edh/geographie/G004415",
        "type": "Feature",
        "properties": {
            "title": "Vinovia ({Lager, praetorium})",
            "summary": null,
            "reciprocal": false
        },
        "links": [
            {
                "type": "closeMatch",
                "identifier": "https://pleiades.stoa.org/places/89316"
            },
            {
                "type": "closeMatch",
                "identifier": "https://www.trismegistos.org/place/13688"
            }
        ]
    },
    {
        "@id": "https://edh.ub.uni-heidelberg.de/edh/geographie/G028394",
        "type": "Feature",
        "properties": {
            "title": "Vinovia, aus ({Escomb, S. John Kirche}, sekundär verwendet)",
            "summary": null,
            "reciprocal": false
        },
        "links": [
            {
                "type": "closeMatch",
                "identifier": "https://pleiades.stoa.org/places/89316"
            },
            {
                "type": "closeMatch",
                "identifier": "https://www.trismegistos.org/place/13688"
            }
        ]
    },
    {
        "@id": "https://edh.ub.uni-heidelberg.de/edh/geographie/G028510",
        "type": "Feature",
        "properties": {
            "title": "Vinovia ({Binchester Farm}, sekundär verwendet)",
            "summary": null,
            "reciprocal": false
        },
        "links": [
            {
                "type": "closeMatch",
                "identifier": "https://pleiades.stoa.org/places/89316"
            },
            {
                "type": "closeMatch",
                "identifier": "https://www.trismegistos.org/place/13688"
            }
        ]
    },
    {
        "@id": "https://edh.ub.uni-heidelberg.de/edh/geographie/G028511",
        "type": "Feature",
        "properties": {
            "title": "Vinovia ({Lager, bei})",
            "summary": null,
            "reciprocal": false
        },
        "links": [
            {
                "type": "closeMatch",
                "identifier": "https://pleiades.stoa.org/places/89316"
            },
            {
                "type": "closeMatch",
                "identifier": "https://www.trismegistos.org/place/13688"
            }
        ]
    },
    {
        "@id": "https://edh.ub.uni-heidelberg.de/edh/geographie/G032565",
        "type": "Feature",
        "properties": {
            "title": "Vinovia ({Lager}, sekundär verwendet)",
            "summary": null,
            "reciprocal": false
        },
        "links": [
            {
                "type": "closeMatch",
                "identifier": "https://pleiades.stoa.org/places/89316"
            }
        ]
    },
    {
        "@id": "https://itiner-e.org/route-segment/13099",
        "type": "Feature",
        "properties": {
            "title": "13099 Vinovia",
            "summary": "Hypothetical Main Road (Itinerarium Antonini)",
            "reciprocal": false
        },
        "links": [
            {
                "type": "relatedMatch",
                "identifier": "https://pleiades.stoa.org/places/89316"
            }
        ]
    },
    {
        "@id": "https://itiner-e.org/route-segment/13101",
        "type": "Feature",
        "properties": {
            "title": "13101 Lewis 274",
            "summary": "Hypothetical Main Road (Straight line conjecture by Joseph Lewis)",
            "reciprocal": false
        },
        "links": [
            {
                "type": "relatedMatch",
                "identifier": "https://pleiades.stoa.org/places/89316"
            }
        ]
    },
    {
        "@id": "https://itiner-e.org/route-segment/14235",
        "type": "Feature",
        "properties": {
            "title": "14235 Eburacum-Vinovia",
            "summary": "Conjectured Main Road (Itinerarium Antonini, Dere Street)",
            "reciprocal": false
        },
        "links": [
            {
                "type": "relatedMatch",
                "identifier": "https://pleiades.stoa.org/places/89316"
            }
        ]
    },
    {
        "@id": "https://itiner-e.org/route-segment/27332",
        "type": "Feature",
        "properties": {
            "title": "27332 Lavatris-Bishop Auckland",
            "summary": "Conjectured Main Road",
            "reciprocal": false
        },
        "links": [
            {
                "type": "relatedMatch",
                "identifier": "https://pleiades.stoa.org/places/496316189"
            },
            {
                "type": "relatedMatch",
                "identifier": "https://pleiades.stoa.org/places/89224"
            },
            {
                "type": "relatedMatch",
                "identifier": "https://pleiades.stoa.org/places/89316"
            }
        ]
    },
    {
        "@id": "https://itiner-e.org/route-segment/27580",
        "type": "Feature",
        "properties": {
            "title": "27580 Vinovia-Bremenium",
            "summary": "Conjectured Main Road (Itinerarium Antonini, Dere Street)",
            "reciprocal": false
        },
        "links": [
            {
                "type": "relatedMatch",
                "identifier": "https://pleiades.stoa.org/places/89152"
            },
            {
                "type": "relatedMatch",
                "identifier": "https://pleiades.stoa.org/places/89201"
            },
            {
                "type": "relatedMatch",
                "identifier": "https://pleiades.stoa.org/places/89230"
            },
            {
                "type": "relatedMatch",
                "identifier": "https://pleiades.stoa.org/places/89314"
            },
            {
                "type": "relatedMatch",
                "identifier": "https://pleiades.stoa.org/places/89316"
            }
        ]
    },
    {
        "@id": "https://itiner-e.org/route-segment/28054",
        "type": "Feature",
        "properties": {
            "title": "28054 Eburacum-Vinovia",
            "summary": "Conjectured Main Road (Itinerarium Antonini, Dere Street)",
            "reciprocal": false
        },
        "links": [
            {
                "type": "relatedMatch",
                "identifier": "https://pleiades.stoa.org/places/89316"
            }
        ]
    },
    {
        "@id": "https://itiner-e.org/route-segment/28056",
        "type": "Feature",
        "properties": {
            "title": "28056 Eburacum-Vinovia",
            "summary": "Conjectured Main Road (Itinerarium Antonini, Dere Street)",
            "reciprocal": false
        },
        "links": [
            {
                "type": "relatedMatch",
                "identifier": "https://pleiades.stoa.org/places/267388585"
            },
            {
                "type": "relatedMatch",
                "identifier": "https://pleiades.stoa.org/places/607714945"
            },
            {
                "type": "relatedMatch",
                "identifier": "https://pleiades.stoa.org/places/89143"
            },
            {
                "type": "relatedMatch",
                "identifier": "https://pleiades.stoa.org/places/89316"
            }
        ]
    }
]