{
    "@type": "Place",
    "bbox": [
        12.7191236,
        41.789121,
        12.7191236,
        41.789121
    ],
    "connections": [],
    "connectsWith": [],
    "contributors": [],
    "created": "2021-03-25T14:52:56Z",
    "creators": [
        {
            "homepage": null,
            "name": "Jeffrey Becker",
            "uri": "https://pleiades.stoa.org/author/jbecker",
            "username": "jbecker"
        }
    ],
    "description": "Stone quarries at Molara (Grottaferrata, Italy). Caves produced by quarry activity were also sites of paleochristian activity.",
    "details": "",
    "features": [
        {
            "geometry": {
                "coordinates": [
                    12.7191236,
                    41.789121
                ],
                "type": "Point"
            },
            "id": "osm-location-of-cava-della-molara",
            "properties": {
                "description": "Representative location based on OpenStreetMap",
                "link": "https://pleiades.stoa.org/places/733759513/osm-location-of-cava-della-molara",
                "location_precision": "precise",
                "snippet": "Quarry",
                "title": "OSM location of cava della molara"
            },
            "type": "Feature"
        }
    ],
    "history": [
        {
            "action": "Publish externally",
            "modified": "2022-07-12T20:16:39Z",
            "modifiedBy": "thomase"
        },
        {
            "action": "Submit for review",
            "modified": "2022-07-12T19:24:12Z",
            "modifiedBy": "jbecker"
        },
        {
            "comment": "Edited",
            "modified": "2022-07-12T19:24:07Z",
            "modifiedBy": "jbecker"
        },
        {
            "comment": "created",
            "modified": "2021-03-25T14:52:57Z",
            "modifiedBy": "jbecker"
        },
        {
            "action": "Create",
            "modified": "2021-03-25T14:52:56Z",
            "modifiedBy": "jbecker"
        }
    ],
    "id": "733759513",
    "locations": [
        {
            "@type": "Location",
            "accuracy": "https://pleiades.stoa.org/features/metadata/generic-osm-accuracy-assessment",
            "accuracy_value": 20.0,
            "archaeologicalRemains": "unknown",
            "associationCertainty": "certain",
            "associationCertaintyURI": "https://pleiades.stoa.org/vocabularies/association-certainty/certain",
            "attestations": [],
            "contributors": [],
            "created": "2021-03-25T14:53:17Z",
            "creators": [
                {
                    "homepage": null,
                    "name": "Jeffrey Becker",
                    "uri": "https://pleiades.stoa.org/author/jbecker",
                    "username": "jbecker"
                }
            ],
            "description": "Representative location based on OpenStreetMap",
            "details": "",
            "end": null,
            "featureType": [
                "quarry"
            ],
            "featureTypeURI": [
                "https://pleiades.stoa.org/vocabularies/place-types/quarry"
            ],
            "geometry": {
                "coordinates": [
                    12.7191236,
                    41.789121
                ],
                "type": "Point"
            },
            "history": [
                {
                    "action": "Publish externally",
                    "modified": "2022-07-12T20:16:39Z",
                    "modifiedBy": "thomase"
                },
                {
                    "action": "Submit for review",
                    "modified": "2022-07-12T19:24:12Z",
                    "modifiedBy": "jbecker"
                },
                {
                    "comment": "added OSM location",
                    "modified": "2021-03-25T14:53:32Z",
                    "modifiedBy": "jbecker"
                },
                {
                    "comment": "Location from OSM created by Products.PleiadesEntity.browser.osm.OSMLocationFactory",
                    "modified": "2021-03-25T14:53:17Z",
                    "modifiedBy": "jbecker"
                },
                {
                    "action": "Create",
                    "modified": "2021-03-25T14:53:17Z",
                    "modifiedBy": "jbecker"
                }
            ],
            "id": "osm-location-of-cava-della-molara",
            "locationType": [
                "representative"
            ],
            "locationTypeURI": [
                "https://pleiades.stoa.org/vocabularies/place-types/quarry"
            ],
            "provenance": "OpenStreetMap (Node 7581255266, version 1, osm:changeset=86098532, 2020-06-02T21:07:53Z)",
            "references": [
                {
                    "accessURI": "https://www.openstreetmap.org/browse/node/7581255266",
                    "alternateURI": "",
                    "bibliographicURI": "",
                    "citationDetail": "Node 7581255266",
                    "citationTypeURI": "http://purl.org/spar/cito/citesAsDataSource",
                    "formattedCitation": "osm:node=7581255266",
                    "otherIdentifier": "",
                    "shortTitle": "OSM",
                    "type": "citesAsDataSource"
                }
            ],
            "review_state": "published",
            "start": null,
            "title": "OSM location of cava della molara",
            "uri": "https://pleiades.stoa.org/places/733759513/osm-location-of-cava-della-molara"
        }
    ],
    "names": [],
    "placeTypeURIs": [
        "https://pleiades.stoa.org/vocabularies/place-types/quarry"
    ],
    "placeTypes": [
        "quarry"
    ],
    "provenance": "Pleiades",
    "references": [
        {
            "accessURI": "https://it.wikipedia.org/wiki/Molara_(Grottaferrata)",
            "alternateURI": "",
            "bibliographicURI": "https://www.zotero.org/groups/pleiades/items/UMFZH98D",
            "citationDetail": "Molara (Grottaferrata)",
            "citationTypeURI": "http://purl.org/spar/cito/seeFurther",
            "formattedCitation": "<div class=\"csl-entry\"><i>Wikipedia: L’enciclopedia libera e collaborativa</i>. Wikimedia Foundation, 2001. https://it.wikipedia.org.</div>",
            "otherIdentifier": "",
            "shortTitle": "Wikipedia (Italian)",
            "type": "seeFurther"
        }
    ],
    "reprPoint": [
        12.7191236,
        41.789121
    ],
    "review_state": "published",
    "rights": "Copyright © The Contributors. Sharing and remixing permitted under terms of the Creative Commons Attribution 3.0 License (cc-by).",
    "subject": [],
    "title": "Quarries at Molara (Grottaferrata)",
    "type": "FeatureCollection",
    "uri": "https://pleiades.stoa.org/places/733759513"
}