{
    "@type": "Place",
    "bbox": [
        26.1985755,
        39.8998617,
        26.1997716,
        39.900779
    ],
    "connections": [
        {
            "@type": "Connection",
            "associationCertainty": "certain",
            "attestations": [],
            "connectionType": "part_of_regional",
            "connectionTypeURI": "https://pleiades.stoa.org/vocabularies/relationship-types/part_of_regional",
            "connectsTo": "https://pleiades.stoa.org/places/550944",
            "contributors": [
                {
                    "homepage": null,
                    "name": "Jeffrey Becker",
                    "uri": "https://pleiades.stoa.org/author/jbecker",
                    "username": "jbecker"
                }
            ],
            "created": "2016-07-13T13:53:03Z",
            "creators": [
                {
                    "homepage": null,
                    "name": "Sean Gillies",
                    "uri": "https://pleiades.stoa.org/author/sgillies",
                    "username": "sgillies"
                }
            ],
            "description": "",
            "details": "",
            "end": null,
            "history": [
                {
                    "comment": "reference",
                    "modified": "2024-03-06T04:18:12Z",
                    "modifiedBy": "jbecker"
                },
                {
                    "action": "Publish externally",
                    "modified": "2016-07-13T13:53:03Z",
                    "modifiedBy": "admin"
                },
                {
                    "action": "Submit for review",
                    "modified": "2016-07-13T13:53:03Z",
                    "modifiedBy": "admin"
                },
                {
                    "action": "Create",
                    "modified": "2016-07-13T13:53:03Z",
                    "modifiedBy": "admin"
                }
            ],
            "id": "550944",
            "provenance": "Pleiades",
            "references": [
                {
                    "accessURI": "http://www.jstor.org/stable/30103104",
                    "alternateURI": "",
                    "bibliographicURI": "https://www.zotero.org/groups/pleiades/items/BJ8443ET",
                    "citationDetail": "",
                    "citationTypeURI": "http://purl.org/spar/cito/seeFurther",
                    "formattedCitation": "<div class=\"csl-entry\">Cook, J.M. “Cities in and around the Troad.” <i>The Annual of the British School at Athens</i> 83 (1988): 7–19. http://www.jstor.org/stable/30103104.</div>",
                    "otherIdentifier": "",
                    "shortTitle": "Cook 1988",
                    "type": "seeFurther"
                }
            ],
            "review_state": "published",
            "start": null,
            "title": "Troas (region)",
            "uri": "https://pleiades.stoa.org/places/897256486/550944"
        }
    ],
    "connectsWith": [
        "https://pleiades.stoa.org/places/550944"
    ],
    "contributors": [
        {
            "homepage": null,
            "name": "Tom Elliott",
            "uri": "https://pleiades.stoa.org/author/thomase",
            "username": "thomase"
        }
    ],
    "created": "2016-06-09T17:12:38Z",
    "creators": [
        {
            "homepage": null,
            "name": "Jeffrey Becker",
            "uri": "https://pleiades.stoa.org/author/jbecker",
            "username": "jbecker"
        }
    ],
    "description": "Uvecik Tepe or Üvecik Tepe is a tumulus in the Troad built for one Festus, a freedman of the emperor Caracalla.",
    "details": "",
    "features": [
        {
            "geometry": {
                "coordinates": [
                    [
                        26.1994125,
                        39.9007427
                    ],
                    [
                        26.199575,
                        39.9006625
                    ],
                    [
                        26.1996892,
                        39.9005556
                    ],
                    [
                        26.1997568,
                        39.9004274
                    ],
                    [
                        26.1997716,
                        39.9002895
                    ],
                    [
                        26.1997322,
                        39.9001546
                    ],
                    [
                        26.1996423,
                        39.9000347
                    ],
                    [
                        26.19951,
                        39.8999408
                    ],
                    [
                        26.1993473,
                        39.8998813
                    ],
                    [
                        26.1991689,
                        39.8998617
                    ],
                    [
                        26.1989909,
                        39.8998837
                    ],
                    [
                        26.1988189,
                        39.8999512
                    ],
                    [
                        26.1986838,
                        39.9000572
                    ],
                    [
                        26.1985998,
                        39.9001907
                    ],
                    [
                        26.1985755,
                        39.9003378
                    ],
                    [
                        26.1986135,
                        39.9004831
                    ],
                    [
                        26.1987099,
                        39.9006116
                    ],
                    [
                        26.1988545,
                        39.9007098
                    ],
                    [
                        26.1990325,
                        39.9007677
                    ],
                    [
                        26.1992251,
                        39.900779
                    ],
                    [
                        26.1994125,
                        39.9007427
                    ]
                ],
                "type": "LineString"
            },
            "id": "osm-location-of-tumulus",
            "properties": {
                "description": "Representative location based on OpenStreetMap.",
                "link": "https://pleiades.stoa.org/places/897256486/osm-location-of-tumulus",
                "location_precision": "precise",
                "snippet": "Tumulus, ; 30 BC - AD 640",
                "title": "OSM location of tumulus"
            },
            "type": "Feature"
        }
    ],
    "history": [
        {
            "comment": "wikidata Üvecik Tepe (Q100138106)",
            "modified": "2024-12-04T23:55:00Z",
            "modifiedBy": "jbecker"
        },
        {
            "comment": "update references",
            "modified": "2024-03-06T04:17:16Z",
            "modifiedBy": "jbecker"
        },
        {
            "action": "Publish externally",
            "modified": "2016-06-12T14:47:00Z",
            "modifiedBy": "thomase"
        },
        {
            "comment": "refined citations and added zotero links",
            "modified": "2016-06-12T14:45:10Z",
            "modifiedBy": "thomase"
        },
        {
            "comment": "added Alcock reference",
            "modified": "2016-06-12T14:24:09Z",
            "modifiedBy": "thomase"
        },
        {
            "action": "Submit for review",
            "modified": "2016-06-09T17:30:56Z",
            "modifiedBy": "jbecker"
        },
        {
            "comment": "added cnxn",
            "modified": "2016-06-09T17:18:13Z",
            "modifiedBy": "jbecker"
        },
        {
            "comment": "added references",
            "modified": "2016-06-09T17:17:01Z",
            "modifiedBy": "jbecker"
        },
        {
            "comment": "created place",
            "modified": "2016-06-09T17:12:45Z",
            "modifiedBy": "jbecker"
        },
        {
            "action": "Create",
            "modified": "2016-06-09T17:12:38Z",
            "modifiedBy": "jbecker"
        }
    ],
    "id": "897256486",
    "locations": [
        {
            "@type": "Location",
            "accuracy": "https://pleiades.stoa.org/features/metadata/generic-osm-accuracy-assessment",
            "accuracy_value": 20.0,
            "archaeologicalRemains": "unknown",
            "associationCertainty": "certain",
            "associationCertaintyURI": "https://pleiades.stoa.org/vocabularies/association-certainty/certain",
            "attestations": [
                {
                    "confidence": "confident",
                    "confidenceURI": "https://pleiades.stoa.org/vocabularies/attestation-confidence/confident",
                    "timePeriod": "roman-early-empire-late-antique",
                    "timePeriodURI": "https://pleiades.stoa.org/vocabularies/time-periods/roman-early-empire-late-antique"
                }
            ],
            "contributors": [],
            "created": "2016-06-09T17:14:58Z",
            "creators": [
                {
                    "homepage": null,
                    "name": "Jeffrey Becker",
                    "uri": "https://pleiades.stoa.org/author/jbecker",
                    "username": "jbecker"
                }
            ],
            "description": "Representative location based on OpenStreetMap.",
            "details": "",
            "end": 640,
            "featureType": [
                "tumulus",
                ""
            ],
            "featureTypeURI": [
                "https://pleiades.stoa.org/vocabularies/place-types/tumulus",
                "https://pleiades.stoa.org/vocabularies/place-types/"
            ],
            "geometry": {
                "coordinates": [
                    [
                        26.1994125,
                        39.9007427
                    ],
                    [
                        26.199575,
                        39.9006625
                    ],
                    [
                        26.1996892,
                        39.9005556
                    ],
                    [
                        26.1997568,
                        39.9004274
                    ],
                    [
                        26.1997716,
                        39.9002895
                    ],
                    [
                        26.1997322,
                        39.9001546
                    ],
                    [
                        26.1996423,
                        39.9000347
                    ],
                    [
                        26.19951,
                        39.8999408
                    ],
                    [
                        26.1993473,
                        39.8998813
                    ],
                    [
                        26.1991689,
                        39.8998617
                    ],
                    [
                        26.1989909,
                        39.8998837
                    ],
                    [
                        26.1988189,
                        39.8999512
                    ],
                    [
                        26.1986838,
                        39.9000572
                    ],
                    [
                        26.1985998,
                        39.9001907
                    ],
                    [
                        26.1985755,
                        39.9003378
                    ],
                    [
                        26.1986135,
                        39.9004831
                    ],
                    [
                        26.1987099,
                        39.9006116
                    ],
                    [
                        26.1988545,
                        39.9007098
                    ],
                    [
                        26.1990325,
                        39.9007677
                    ],
                    [
                        26.1992251,
                        39.900779
                    ],
                    [
                        26.1994125,
                        39.9007427
                    ]
                ],
                "type": "LineString"
            },
            "history": [
                {
                    "comment": "Reimported full way geometry and updated provenance",
                    "modified": "2024-12-04T23:53:26Z",
                    "modifiedBy": "jbecker"
                },
                {
                    "action": "Publish externally",
                    "modified": "2016-06-12T14:47:01Z",
                    "modifiedBy": "thomase"
                },
                {
                    "action": "Submit for review",
                    "modified": "2016-06-09T17:31:02Z",
                    "modifiedBy": "jbecker"
                },
                {
                    "comment": "added location",
                    "modified": "2016-06-09T17:15:38Z",
                    "modifiedBy": "jbecker"
                },
                {
                    "comment": "Location from OSM created by Products.PleiadesEntity.browser.osm.OSMLocationFactory",
                    "modified": "2016-06-09T17:14:59Z",
                    "modifiedBy": "jbecker"
                },
                {
                    "action": "Create",
                    "modified": "2016-06-09T17:14:58Z",
                    "modifiedBy": "jbecker"
                }
            ],
            "id": "osm-location-of-tumulus",
            "locationType": [
                "representative"
            ],
            "locationTypeURI": [
                "https://pleiades.stoa.org/vocabularies/place-types/tumulus",
                "https://pleiades.stoa.org/vocabularies/place-types/"
            ],
            "provenance": "OpenStreetMap (Way 175564604, version 6, osm:changeset=138538408, 2023-07-15T10:14:29Z)",
            "references": [
                {
                    "accessURI": "http://www.openstreetmap.org/browse/way/175564604",
                    "alternateURI": "",
                    "bibliographicURI": "",
                    "citationDetail": "Way 175564604",
                    "citationTypeURI": "http://purl.org/spar/cito/citesAsDataSource",
                    "formattedCitation": "osm:way=175564604",
                    "otherIdentifier": " ",
                    "shortTitle": "OSM",
                    "type": "citesAsDataSource"
                }
            ],
            "review_state": "published",
            "start": -30,
            "title": "OSM location of tumulus",
            "uri": "https://pleiades.stoa.org/places/897256486/osm-location-of-tumulus"
        }
    ],
    "names": [],
    "placeTypeURIs": [
        "https://pleiades.stoa.org/vocabularies/place-types/tumulus"
    ],
    "placeTypes": [
        "tumulus"
    ],
    "provenance": "Pleiades",
    "references": [
        {
            "accessURI": "http://www.livius.org/pictures/a2/turkey/troy/uvecik-tepe/",
            "alternateURI": "",
            "bibliographicURI": "https://www.zotero.org/groups/pleiades/items/726HWVKS",
            "citationDetail": "Uvecik Tepe (photo)",
            "citationTypeURI": "http://purl.org/spar/cito/seeFurther",
            "formattedCitation": "<div class=\"csl-entry\">Lendering, Jona. <i>Livius - Articles on Ancient History</i>, 1995. http://www.livius.org/.</div>",
            "otherIdentifier": " ",
            "shortTitle": "Livius.org",
            "type": "seeFurther"
        },
        {
            "accessURI": "https://www.cambridge.org/core/books/archaeology-of-greek-and-roman-troy/6EFCE946B7A7B5122708AD52A859EB69",
            "alternateURI": "",
            "bibliographicURI": "https://www.zotero.org/groups/pleiades/items/3MNDDD98",
            "citationDetail": "260",
            "citationTypeURI": "http://purl.org/spar/cito/seeFurther",
            "formattedCitation": "<div class=\"csl-entry\">Rose, Charles Brian. <i>The Archaeology of Greek and Roman Troy</i>. New York: Cambridge University Press, 2014. https://www.cambridge.org/core/books/archaeology-of-greek-and-roman-troy/6EFCE946B7A7B5122708AD52A859EB69.</div>",
            "otherIdentifier": " ",
            "shortTitle": "Rose 2014",
            "type": "seeFurther"
        },
        {
            "accessURI": "",
            "alternateURI": "",
            "bibliographicURI": "https://www.zotero.org/groups/pleiades/items/5S8RKNQF",
            "citationDetail": "pp. 12 (map) and 15",
            "citationTypeURI": "http://purl.org/spar/cito/seeFurther",
            "formattedCitation": "<div class=\"csl-entry\">Luce, John V. “The Case for Historical Significance in Homer’s Landmarks at Troia.” In <i>Troia and the Troad: Scientific Approaches</i>, edited by Günther A Wagner, Ernst Pernicka, and Hans-Peter Uerpmann, 9–30. Berlin; New York: Springer, 2003.</div>",
            "otherIdentifier": " ",
            "shortTitle": "Luce 2003",
            "type": "seeFurther"
        },
        {
            "accessURI": "",
            "alternateURI": "",
            "bibliographicURI": "https://www.zotero.org/groups/pleiades/items/XGE7I22G",
            "citationDetail": "pp. 161-162",
            "citationTypeURI": "http://purl.org/spar/cito/seeFurther",
            "formattedCitation": "<div class=\"csl-entry\">Alcock, S. “Material Witness: An Archeological Context for the Heroikos.” In <i>Philostratus’s Heroikos. Religion and Cultural Identity in the Third Century</i>, edited by Jennifer K Berenson Maclean and Ellen Bradshaw Aitken, 159–68. Writings from the Greco-Roman World 5. Leiden; Boston: Brill, 2005.</div>",
            "otherIdentifier": " ",
            "shortTitle": "Alcock 2005",
            "type": "seeFurther"
        },
        {
            "accessURI": "https://www.wikidata.org/wiki/Q100138106",
            "alternateURI": "",
            "bibliographicURI": "https://www.zotero.org/groups/pleiades/items/BCQIKDKS",
            "citationDetail": "Üvecik Tepe (Q100138106)",
            "citationTypeURI": "http://purl.org/spar/cito/citesAsRelated",
            "formattedCitation": "<div class=\"csl-entry\"><i>Wikidata: The Free Knowledge Base That Anyone Can Edit</i>. Wikimedia Foundation, 2014. https://www.wikidata.org/.</div>",
            "otherIdentifier": "",
            "shortTitle": "Wikidata",
            "type": "citesAsRelated"
        }
    ],
    "reprPoint": [
        26.199174309437744,
        39.90032106545745
    ],
    "review_state": "published",
    "rights": "Copyright © The Contributors. Sharing and remixing permitted under terms of the Creative Commons Attribution 3.0 License (cc-by).",
    "subject": [],
    "title": "Uvecik Tepe",
    "type": "FeatureCollection",
    "uri": "https://pleiades.stoa.org/places/897256486"
}