{
    "@type": "Place",
    "bbox": [
        -5.9981701,
        42.0898132,
        -5.9981701,
        42.0898132
    ],
    "connections": [],
    "connectsWith": [],
    "contributors": [
        {
            "name": "DARMC",
            "username": null
        },
        {
            "name": "R. Talbert",
            "username": null
        },
        {
            "homepage": null,
            "name": "Sean Gillies",
            "uri": "https://pleiades.stoa.org/author/sgillies",
            "username": "sgillies"
        },
        {
            "homepage": null,
            "name": "Tom Elliott",
            "uri": "https://pleiades.stoa.org/author/thomase",
            "username": "thomase"
        },
        {
            "homepage": null,
            "name": "Jeffrey Becker",
            "uri": "https://pleiades.stoa.org/author/jbecker",
            "username": "jbecker"
        }
    ],
    "created": "2010-09-24T16:46:27Z",
    "creators": [
        {
            "name": "E.W. Haley",
            "username": null
        }
    ],
    "description": "A Roman legionary encampment (castrum) associated with the Legio X Gemina that later developed into a Roman town. The site is located in the Vidriales valley in the province of Zamora (Castilla y Leon).",
    "details": "<p>The Barrington Atlas Directory notes: Rosinos de Vidriales</p>",
    "features": [
        {
            "geometry": {
                "coordinates": [
                    [
                        -5.998392,
                        42.0898966
                    ],
                    [
                        -5.9984638,
                        42.0899109
                    ],
                    [
                        -5.9985166,
                        42.0899103
                    ],
                    [
                        -5.9985764,
                        42.089894
                    ],
                    [
                        -5.9986196,
                        42.0898727
                    ],
                    [
                        -5.9986453,
                        42.089854
                    ],
                    [
                        -5.9991122,
                        42.089267
                    ],
                    [
                        -5.9991629,
                        42.0892033
                    ],
                    [
                        -5.9996543,
                        42.0885855
                    ],
                    [
                        -5.9996816,
                        42.0885466
                    ],
                    [
                        -5.9996871,
                        42.0884996
                    ],
                    [
                        -5.9996806,
                        42.0884508
                    ],
                    [
                        -5.9996467,
                        42.0884072
                    ],
                    [
                        -5.9996127,
                        42.0883754
                    ],
                    [
                        -5.9993129,
                        42.0882445
                    ],
                    [
                        -5.9981352,
                        42.0877304
                    ],
                    [
                        -5.9973503,
                        42.0873878
                    ],
                    [
                        -5.9972719,
                        42.0873681
                    ],
                    [
                        -5.9972112,
                        42.0873705
                    ],
                    [
                        -5.997164,
                        42.0873796
                    ],
                    [
                        -5.9971004,
                        42.0874092
                    ],
                    [
                        -5.9970536,
                        42.0874404
                    ],
                    [
                        -5.9967431,
                        42.0877988
                    ],
                    [
                        -5.9965251,
                        42.088072
                    ],
                    [
                        -5.9964496,
                        42.0881666
                    ],
                    [
                        -5.9960101,
                        42.0887172
                    ],
                    [
                        -5.9959873,
                        42.0887728
                    ],
                    [
                        -5.995988,
                        42.0888168
                    ],
                    [
                        -5.9959999,
                        42.0888492
                    ],
                    [
                        -5.9960533,
                        42.0889099
                    ],
                    [
                        -5.9968033,
                        42.0892421
                    ],
                    [
                        -5.9968769,
                        42.0892724
                    ],
                    [
                        -5.998392,
                        42.0898966
                    ]
                ],
                "type": "LineString"
            },
            "id": "location-of-castrum",
            "properties": {
                "description": "Representative location based on OpenStreetMap",
                "link": "https://pleiades.stoa.org/places/236598/location-of-castrum",
                "location_precision": "precise",
                "snippet": "Fort; 30 BC - AD 300",
                "title": "OSM location of Petavonium"
            },
            "type": "Feature"
        }
    ],
    "history": [
        {
            "comment": "updates",
            "modified": "2020-12-22T14:33:05Z",
            "modifiedBy": "jbecker"
        },
        {
            "comment": "Edited",
            "modified": "2020-12-22T14:25:59Z",
            "modifiedBy": "jbecker"
        },
        {
            "comment": "added reference",
            "modified": "2013-12-05T18:43:39Z",
            "modifiedBy": "jbecker"
        },
        {
            "comment": "Location updates and tags from Johan Ahlfeldt's (jahlfeldt) Digital Atlas of the Roman Empire in October 2012",
            "modified": "2012-10-20T23:49:30Z",
            "modifiedBy": "sgillies"
        },
        {
            "comment": "Global migration and reindexing of citations and provenance, February 2012",
            "modified": "2012-02-15T03:24:01Z",
            "modifiedBy": "admin"
        },
        {
            "comment": "New locations, coordinates, and metadata from Harvard's DARMC project. See http://atlantides.org/trac/pleiades/wiki/PlaceUpgradesAndMigrations",
            "modified": "2011-03-09T23:33:37Z",
            "modifiedBy": "sgillies"
        },
        {
            "comment": "Detail text updated from former modernLocation. See http://atlantides.org/trac/pleiades/wiki/PlaceDetailsUpgrade",
            "modified": "2011-01-14T19:12:52Z",
            "modifiedBy": "sgillies"
        },
        {
            "action": "Publish externally",
            "modified": "2010-09-24T18:47:26Z",
            "modifiedBy": "thomase"
        },
        {
            "action": "Submit for review",
            "modified": "2010-09-24T16:53:52Z",
            "modifiedBy": "sgillies"
        },
        {
            "action": "Create",
            "modified": "2010-09-24T16:46:27Z",
            "modifiedBy": "sgillies"
        }
    ],
    "id": "236598",
    "locations": [
        {
            "@type": "Location",
            "accuracy": "https://pleiades.stoa.org/features/metadata/generic-osm-accuracy-assessment",
            "accuracy_value": 20.0,
            "archaeologicalRemains": "unknown",
            "associationCertainty": "certain",
            "associationCertaintyURI": "https://pleiades.stoa.org/vocabularies/association-certainty/certain",
            "attestations": [
                {
                    "confidence": "confident",
                    "confidenceURI": "https://pleiades.stoa.org/vocabularies/attestation-confidence/confident",
                    "timePeriod": "roman",
                    "timePeriodURI": "https://pleiades.stoa.org/vocabularies/time-periods/roman"
                }
            ],
            "contributors": [],
            "created": "2023-04-04T21:21:33Z",
            "creators": [
                {
                    "homepage": null,
                    "name": "Jeffrey Becker",
                    "uri": "https://pleiades.stoa.org/author/jbecker",
                    "username": "jbecker"
                }
            ],
            "description": "Representative location based on OpenStreetMap",
            "details": "",
            "end": 300,
            "featureType": [
                "fort"
            ],
            "featureTypeURI": [
                "https://pleiades.stoa.org/vocabularies/place-types/fort"
            ],
            "geometry": {
                "coordinates": [
                    [
                        -5.998392,
                        42.0898966
                    ],
                    [
                        -5.9984638,
                        42.0899109
                    ],
                    [
                        -5.9985166,
                        42.0899103
                    ],
                    [
                        -5.9985764,
                        42.089894
                    ],
                    [
                        -5.9986196,
                        42.0898727
                    ],
                    [
                        -5.9986453,
                        42.089854
                    ],
                    [
                        -5.9991122,
                        42.089267
                    ],
                    [
                        -5.9991629,
                        42.0892033
                    ],
                    [
                        -5.9996543,
                        42.0885855
                    ],
                    [
                        -5.9996816,
                        42.0885466
                    ],
                    [
                        -5.9996871,
                        42.0884996
                    ],
                    [
                        -5.9996806,
                        42.0884508
                    ],
                    [
                        -5.9996467,
                        42.0884072
                    ],
                    [
                        -5.9996127,
                        42.0883754
                    ],
                    [
                        -5.9993129,
                        42.0882445
                    ],
                    [
                        -5.9981352,
                        42.0877304
                    ],
                    [
                        -5.9973503,
                        42.0873878
                    ],
                    [
                        -5.9972719,
                        42.0873681
                    ],
                    [
                        -5.9972112,
                        42.0873705
                    ],
                    [
                        -5.997164,
                        42.0873796
                    ],
                    [
                        -5.9971004,
                        42.0874092
                    ],
                    [
                        -5.9970536,
                        42.0874404
                    ],
                    [
                        -5.9967431,
                        42.0877988
                    ],
                    [
                        -5.9965251,
                        42.088072
                    ],
                    [
                        -5.9964496,
                        42.0881666
                    ],
                    [
                        -5.9960101,
                        42.0887172
                    ],
                    [
                        -5.9959873,
                        42.0887728
                    ],
                    [
                        -5.995988,
                        42.0888168
                    ],
                    [
                        -5.9959999,
                        42.0888492
                    ],
                    [
                        -5.9960533,
                        42.0889099
                    ],
                    [
                        -5.9968033,
                        42.0892421
                    ],
                    [
                        -5.9968769,
                        42.0892724
                    ],
                    [
                        -5.998392,
                        42.0898966
                    ]
                ],
                "type": "LineString"
            },
            "history": [
                {
                    "comment": "Reimported full way geometry and updated provenance",
                    "modified": "2023-04-05T00:24:44Z",
                    "modifiedBy": "jbecker"
                },
                {
                    "comment": "update",
                    "modified": "2020-12-22T14:28:14Z",
                    "modifiedBy": "jbecker"
                },
                {
                    "action": "Publish externally",
                    "modified": "2013-12-20T02:10:36Z",
                    "modifiedBy": "jbecker"
                },
                {
                    "action": "Submit for review",
                    "modified": "2013-12-05T18:45:52Z",
                    "modifiedBy": "jbecker"
                },
                {
                    "comment": "added location",
                    "modified": "2013-12-05T18:45:15Z",
                    "modifiedBy": "jbecker"
                },
                {
                    "comment": "Location from OSM created by Products.PleiadesEntity.browser.osm.OSMLocationFactory",
                    "modified": "2013-12-05T18:44:15Z",
                    "modifiedBy": "jbecker"
                },
                {
                    "action": "Create",
                    "modified": "2013-12-05T18:44:10Z",
                    "modifiedBy": "jbecker"
                }
            ],
            "id": "location-of-castrum",
            "locationType": [
                "representative"
            ],
            "locationTypeURI": [
                "https://pleiades.stoa.org/vocabularies/place-types/fort"
            ],
            "provenance": "OpenStreetMap (Way 250192426, version 7, osm:changeset=133037465, 2023-02-26T11:07:35Z)",
            "references": [
                {
                    "accessURI": "http://www.openstreetmap.org/browse/way/250192426",
                    "alternateURI": "",
                    "bibliographicURI": "",
                    "citationDetail": "Way 250192426",
                    "citationTypeURI": "http://purl.org/spar/cito/citesAsDataSource",
                    "formattedCitation": "osm:way=250192426",
                    "otherIdentifier": " ",
                    "shortTitle": "OSM",
                    "type": "citesAsDataSource"
                }
            ],
            "review_state": "published",
            "start": -30,
            "title": "OSM location of Petavonium",
            "uri": "https://pleiades.stoa.org/places/236598/location-of-castrum"
        }
    ],
    "names": [
        {
            "@type": "Name",
            "associationCertainty": "certain",
            "associationCertaintyURI": "https://pleiades.stoa.org/vocabularies/association-certainty/certain",
            "attestations": [
                {
                    "confidence": "confident",
                    "confidenceURI": "https://pleiades.stoa.org/vocabularies/attestation-confidence/confident",
                    "timePeriod": "roman",
                    "timePeriodURI": "https://pleiades.stoa.org/vocabularies/time-periods/roman"
                },
                {
                    "confidence": "confident",
                    "confidenceURI": "https://pleiades.stoa.org/vocabularies/attestation-confidence/confident",
                    "timePeriod": "late-antique",
                    "timePeriodURI": "https://pleiades.stoa.org/vocabularies/time-periods/late-antique"
                }
            ],
            "attested": "",
            "contributors": [
                {
                    "name": "R. Talbert",
                    "username": null
                },
                {
                    "name": "T. Elliott",
                    "username": null
                },
                {
                    "homepage": null,
                    "name": "Sean Gillies",
                    "uri": "https://pleiades.stoa.org/author/sgillies",
                    "username": "sgillies"
                }
            ],
            "created": "2010-09-24T16:46:28Z",
            "creators": [
                {
                    "name": "E.W. Haley",
                    "username": null
                }
            ],
            "description": "",
            "details": "",
            "end": 640,
            "history": [
                {
                    "comment": "Global migration and reindexing of citations and provenance, February 2012",
                    "modified": "2012-02-15T03:24:02Z",
                    "modifiedBy": "admin"
                },
                {
                    "action": "Publish externally",
                    "modified": "2010-09-24T18:47:26Z",
                    "modifiedBy": "thomase"
                },
                {
                    "action": "Submit for review",
                    "modified": "2010-09-24T16:53:52Z",
                    "modifiedBy": "sgillies"
                },
                {
                    "action": "Create",
                    "modified": "2010-09-24T16:46:28Z",
                    "modifiedBy": "sgillies"
                }
            ],
            "id": "petavonium",
            "language": "",
            "nameType": "geographic",
            "provenance": "Barrington Atlas: BAtlas 24 F2 Petavonium",
            "references": [],
            "review_state": "published",
            "romanized": "Petavonium",
            "start": -30,
            "transcriptionAccuracy": "accurate",
            "transcriptionCompleteness": "complete",
            "uri": "https://pleiades.stoa.org/places/236598/petavonium"
        }
    ],
    "placeTypeURIs": [
        "https://pleiades.stoa.org/vocabularies/place-types/fort"
    ],
    "placeTypes": [
        "fort"
    ],
    "provenance": "Barrington Atlas: BAtlas 24 F2 Petavonium",
    "references": [
        {
            "accessURI": "http://www.worldcat.org/oclc/43970336",
            "alternateURI": "",
            "bibliographicURI": "https://www.zotero.org/groups/pleiades/items/MIAGQ5C6",
            "citationDetail": "24 F2 Petavonium",
            "citationTypeURI": "http://purl.org/spar/cito/seeFurther",
            "formattedCitation": "<div class=\"csl-entry\">Talbert, Richard J. A., ed. <i>Barrington Atlas of the Greek and Roman World</i>. Princeton, N.J.: Princeton University Press, 2000. http://www.worldcat.org/oclc/43970336.</div>",
            "otherIdentifier": " ",
            "shortTitle": "BAtlas",
            "type": "seeFurther"
        },
        {
            "accessURI": "http://www.worldcat.org/oclc/31397775",
            "alternateURI": "",
            "bibliographicURI": "https://www.zotero.org/groups/pleiades/items/H6EE4IV4",
            "citationDetail": "177",
            "citationTypeURI": "http://purl.org/spar/cito/seeFurther",
            "formattedCitation": "<div class=\"csl-entry\">Fatás Cabeza, Guillermo, Adela Cepas, José Ignacio Reguera Cardiel, and José Manuel Abascal Palazón. <i>Tabula Imperii Romani : K30 Madrid : Caesaraugusta - Clunia : escala 1:1.000.000 : base geográfica, Instituto Geográfico Nacional</i>. Tabula Imperii Romani, K30. Madrid. Madrid: Ministerio de Cultura; Union académique internationale; Instituto Geográfico Nacional (Spain), 1993. http://www.worldcat.org/oclc/31397775.</div>",
            "otherIdentifier": "",
            "shortTitle": "TIR Caesaraugusta",
            "type": "seeFurther"
        },
        {
            "accessURI": "https://es.wikipedia.org/wiki/Petavonium",
            "alternateURI": "",
            "bibliographicURI": "https://www.zotero.org/groups/2533/pleiades/items/itemKey/LPYQ8SZL",
            "citationDetail": "Petavonium",
            "citationTypeURI": "http://purl.org/spar/cito/seeFurther",
            "formattedCitation": "Wikipedia: la enciclopedia de contenido libre (2001-), Petavonium.",
            "otherIdentifier": " ",
            "shortTitle": "Wikipedia (Spanish)",
            "type": "seeFurther"
        },
        {
            "accessURI": "",
            "alternateURI": "",
            "bibliographicURI": "https://www.zotero.org/groups/pleiades/items/UJ7SRVWH",
            "citationDetail": "",
            "citationTypeURI": "http://purl.org/spar/cito/seeFurther",
            "formattedCitation": "<div class=\"csl-entry\">Carretero Vaquero, Santiago, and María Victoria Romero Carnicero. “Petavonium: un núcleo civil surgido al abrigo del ejército.” In <i>Emergência e desenvolvimento das cidades romanas no norte da Península Ibérica (Congreso, Porto 1999)</i>, 157–70. Porto: Escola Profissional de Arqueologia, 2000.</div>",
            "otherIdentifier": " ",
            "shortTitle": "Carretero Vaquero 2000",
            "type": "seeFurther"
        },
        {
            "accessURI": "https://darmc.harvard.edu/",
            "alternateURI": "",
            "bibliographicURI": "https://www.zotero.org/groups/pleiades/items/9UD9W75C",
            "citationDetail": "19174",
            "citationTypeURI": "http://purl.org/spar/cito/citesAsRelated",
            "formattedCitation": "<div class=\"csl-entry\">Michael McCormick, Giovanni Zambotti, Leland Grigoli, and Kelly Gibson, eds. <i>The Digital Atlas of Roman and Medieval Civilizations</i>. Cambridge (Massachusetts): Harvard University, 2007. https://darmc.harvard.edu/.</div>",
            "otherIdentifier": "",
            "shortTitle": "DARMC",
            "type": "citesAsRelated"
        },
        {
            "accessURI": "https://www.wikidata.org/wiki/Q6073313",
            "alternateURI": "",
            "bibliographicURI": "https://www.zotero.org/groups/pleiades/items/BCQIKDKS",
            "citationDetail": "Q6073313: Petavonium",
            "citationTypeURI": "http://purl.org/spar/cito/citesAsRelated",
            "formattedCitation": "<div class=\"csl-entry\"><i>Wikidata: The Free Knowledge Base That Anyone Can Edit</i>. Wikimedia Foundation, 2014. https://www.wikidata.org/.</div>",
            "otherIdentifier": "",
            "shortTitle": "Wikidata",
            "type": "citesAsRelated"
        }
    ],
    "reprPoint": [
        -5.9981701,
        42.0898132
    ],
    "review_state": "published",
    "rights": "Copyright © The Contributors. Sharing and remixing permitted under terms of the Creative Commons Attribution 3.0 License (cc-by).",
    "subject": [
        "dare:ancient=1",
        "dare:major=0",
        "dare:feature=fort"
    ],
    "title": "Petavonium",
    "type": "FeatureCollection",
    "uri": "https://pleiades.stoa.org/places/236598"
}