[
    {
        "@id": "http://www.wikidata.org/entity/Q624638",
        "type": "Feature",
        "properties": {
            "title": "Arachosia",
            "summary": "Ancient region of the Persian empire",
            "reciprocal": true
        },
        "links": [
            {
                "type": "closeMatch",
                "identifier": "https://pleiades.stoa.org/places/59692"
            }
        ]
    },
    {
        "@id": "https://topostext.org/place/315650RAra",
        "type": "Feature",
        "properties": {
            "title": "Arachosia (Asia)",
            "summary": "Satrapy of Persia, in SW Afghanistan",
            "reciprocal": true
        },
        "links": [
            {
                "type": "closeMatch",
                "identifier": "https://pleiades.stoa.org/places/59692"
            },
            {
                "type": "closeMatch",
                "identifier": "https://www.wikidata.org/wiki/Q624638"
            }
        ]
    }
]