[
    {
        "@id": "http://www.wikidata.org/entity/Q12880025",
        "type": "Feature",
        "properties": {
            "title": "Lessa",
            "summary": "Ancient acropolis on Kazarma hill",
            "reciprocal": false
        },
        "links": [
            {
                "type": "closeMatch",
                "identifier": "https://pleiades.stoa.org/places/570426"
            }
        ]
    },
    {
        "@id": "https://itiner-e.org/route-segment/21375",
        "type": "Feature",
        "properties": {
            "title": "21375 Argos-Epidauros",
            "summary": "Conjectured Main Road (Tabula Peutingeriana)",
            "reciprocal": false
        },
        "links": [
            {
                "type": "relatedMatch",
                "identifier": "https://pleiades.stoa.org/places/570124"
            },
            {
                "type": "relatedMatch",
                "identifier": "https://pleiades.stoa.org/places/570127"
            },
            {
                "type": "relatedMatch",
                "identifier": "https://pleiades.stoa.org/places/570426"
            },
            {
                "type": "relatedMatch",
                "identifier": "https://pleiades.stoa.org/places/570485"
            },
            {
                "type": "relatedMatch",
                "identifier": "https://pleiades.stoa.org/places/570501"
            },
            {
                "type": "relatedMatch",
                "identifier": "https://pleiades.stoa.org/places/570710"
            },
            {
                "type": "relatedMatch",
                "identifier": "https://pleiades.stoa.org/places/570740"
            },
            {
                "type": "relatedMatch",
                "identifier": "https://pleiades.stoa.org/places/770053487"
            }
        ]
    },
    {
        "@id": "https://itiner-e.org/route-segment/21376",
        "type": "Feature",
        "properties": {
            "title": "21376 Argos-Epidauros",
            "summary": "Conjectured Main Road (Tabula Peutingeriana)",
            "reciprocal": false
        },
        "links": [
            {
                "type": "relatedMatch",
                "identifier": "https://pleiades.stoa.org/places/570127"
            },
            {
                "type": "relatedMatch",
                "identifier": "https://pleiades.stoa.org/places/570228"
            },
            {
                "type": "relatedMatch",
                "identifier": "https://pleiades.stoa.org/places/570426"
            },
            {
                "type": "relatedMatch",
                "identifier": "https://pleiades.stoa.org/places/770053487"
            }
        ]
    },
    {
        "@id": "https://itiner-e.org/route-segment/21379",
        "type": "Feature",
        "properties": {
            "title": "21379 Argos-Asklepeion-Epidauros",
            "summary": "Conjectured Main Road",
            "reciprocal": false
        },
        "links": [
            {
                "type": "relatedMatch",
                "identifier": "https://pleiades.stoa.org/places/570127"
            },
            {
                "type": "relatedMatch",
                "identifier": "https://pleiades.stoa.org/places/570228"
            },
            {
                "type": "relatedMatch",
                "identifier": "https://pleiades.stoa.org/places/570426"
            },
            {
                "type": "relatedMatch",
                "identifier": "https://pleiades.stoa.org/places/570601"
            },
            {
                "type": "relatedMatch",
                "identifier": "https://pleiades.stoa.org/places/770053487"
            }
        ]
    },
    {
        "@id": "https://itiner-e.org/route-segment/21391",
        "type": "Feature",
        "properties": {
            "title": "21391 Asine-Mases",
            "summary": "Conjectured Secondary Road",
            "reciprocal": false
        },
        "links": [
            {
                "type": "relatedMatch",
                "identifier": "https://pleiades.stoa.org/places/570124"
            },
            {
                "type": "relatedMatch",
                "identifier": "https://pleiades.stoa.org/places/570426"
            },
            {
                "type": "relatedMatch",
                "identifier": "https://pleiades.stoa.org/places/570501"
            },
            {
                "type": "relatedMatch",
                "identifier": "https://pleiades.stoa.org/places/770053487"
            }
        ]
    },
    {
        "@id": "https://topostext.org/place/376229ULes",
        "type": "Feature",
        "properties": {
            "title": "Lessa (Epidauria)",
            "summary": "Classical to Roman town, possibly at Kazarma/Arkadiko or Ligourio, Argolid",
            "reciprocal": true
        },
        "links": [
            {
                "type": "closeMatch",
                "identifier": "https://pleiades.stoa.org/places/570426"
            },
            {
                "type": "closeMatch",
                "identifier": "https://www.wikidata.org/wiki/Q12880025"
            }
        ]
    }
]